slcfg/__init__.py
slcfg/config.py
slcfg/environment.py
slcfg/item.py
slcfg/layer.py
slcfg/py.typed
slcfg/util.py
slcfg-0.3.4.dist-info/LICENSE
slcfg-0.3.4.dist-info/METADATA
slcfg-0.3.4.dist-info/WHEEL
slcfg-0.3.4.dist-info/RECORD
